dec64/Base64Decoder.py
dec64/__init__.py
dec64/__main__.py
dec64/file.py
dec64/main.py
dec64/tests/tests.py
dec64-0.0.4.post0.dist-info/licenses/LICENSE
dec64-0.0.4.post0.dist-info/METADATA
dec64-0.0.4.post0.dist-info/WHEEL
dec64-0.0.4.post0.dist-info/entry_points.txt
dec64-0.0.4.post0.dist-info/top_level.txt
dec64-0.0.4.post0.dist-info/RECORD
