Metadata-Version: 2.4
Name: dec64
Version: 0.0.4.post0
Summary: Recursively decode Base64 encoded strings.
Author-email: xdearboy <BigManClub@gmail.com>
Project-URL: Home, https://github.com/xdearboy/dec64
Classifier: Development Status :: 5 - Production/Stable
Classifier: Intended Audience :: Developers
Classifier: License :: OSI Approved :: MIT License
Classifier: Programming Language :: Python :: 3
Classifier: Programming Language :: Python :: 3.6
Classifier: Programming Language :: Python :: 3.7
Classifier: Programming Language :: Python :: 3.8
Classifier: Programming Language :: Python :: 3.9
Classifier: Programming Language :: Python :: 3.10
Classifier: Programming Language :: Python :: 3.11
Requires-Python: >=3.6
License-File: LICENSE
Dynamic: license-file
